test_average/__init__.py
test_average/average.py
basic_package_lol-1.0.4.dist-info/METADATA
basic_package_lol-1.0.4.dist-info/WHEEL
basic_package_lol-1.0.4.dist-info/top_level.txt
basic_package_lol-1.0.4.dist-info/RECORD
